leafsway/__init__.py
leafsway-0.1.0.dist-info/METADATA
leafsway-0.1.0.dist-info/WHEEL
leafsway-0.1.0.dist-info/top_level.txt
leafsway-0.1.0.dist-info/RECORD
